cmdstanpy/__init__.py
cmdstanpy/_version.py
cmdstanpy/cmdstan_args.py
cmdstanpy/compilation.py
cmdstanpy/install_cmdstan.py
cmdstanpy/install_cxx_toolchain.py
cmdstanpy/model.py
cmdstanpy/progress.py
cmdstanpy/py.typed
cmdstanpy/stanfit/__init__.py
cmdstanpy/stanfit/gq.py
cmdstanpy/stanfit/laplace.py
cmdstanpy/stanfit/mcmc.py
cmdstanpy/stanfit/metadata.py
cmdstanpy/stanfit/mle.py
cmdstanpy/stanfit/pathfinder.py
cmdstanpy/stanfit/runset.py
cmdstanpy/stanfit/vb.py
cmdstanpy/utils/__init__.py
cmdstanpy/utils/cmdstan.py
cmdstanpy/utils/command.py
cmdstanpy/utils/data_munging.py
cmdstanpy/utils/filesystem.py
cmdstanpy/utils/json.py
cmdstanpy/utils/logging.py
cmdstanpy/utils/stancsv.py
cmdstanpy_opencl-0.9.70.dist-info/LICENSE.md
cmdstanpy_opencl-0.9.70.dist-info/METADATA
cmdstanpy_opencl-0.9.70.dist-info/WHEEL
cmdstanpy_opencl-0.9.70.dist-info/RECORD
