Metadata-Version: 2.1
Name: cmdstanpy-opencl
Version: 0.9.70
Summary: 
Author: StoffAudioLLC
Author-email: stoffaudio@gmail.com
Requires-Python: >=3.9,<4.0
Classifier: Programming Language :: Python :: 3
Classifier: Programming Language :: Python :: 3.9
Classifier: Programming Language :: Python :: 3.10
Classifier: Programming Language :: Python :: 3.11
Requires-Dist: numpy (>=1.21)
Requires-Dist: pandas
Requires-Dist: stanio (>=0.3.0,<0.4.0)
Requires-Dist: tqdm (>=4.66.1,<5.0.0)
Requires-Dist: twine (>=4.0.2,<5.0.0)
